roi_rectangle/__init__.py
roi_rectangle/roi_rectangle.py
roi_rectangle-1.0.0.dist-info/METADATA
roi_rectangle-1.0.0.dist-info/WHEEL
roi_rectangle-1.0.0.dist-info/top_level.txt
roi_rectangle-1.0.0.dist-info/RECORD
