Metadata-Version: 2.4
Name: roi_rectangle
Version: 1.0.0
Summary: A module for handling rectangular regions of interest (ROI) in images.
Home-page: https://github.com/SJB7777/roi_rectangle
Author: Isaac Yong
Author-email: esakyong1866@naver.com
Classifier: Development Status :: 1 - Planning
Classifier: Intended Audience :: Developers
Classifier: Programming Language :: Python :: 3
Classifier: Operating System :: Unix
Classifier: Operating System :: MacOS :: MacOS X
Classifier: Operating System :: Microsoft :: Windows
Requires-Python: >=3.8
Requires-Dist: numpy
Dynamic: author
Dynamic: author-email
Dynamic: classifier
Dynamic: description
Dynamic: description-content-type
Dynamic: home-page
Dynamic: requires-dist
Dynamic: requires-python
Dynamic: summary
